chopdiff/__init__.py
chopdiff/py.typed
chopdiff/divs/__init__.py
chopdiff/divs/chunk_utils.py
chopdiff/divs/div_elements.py
chopdiff/divs/parse_divs.py
chopdiff/divs/text_node.py
chopdiff/docs/__init__.py
chopdiff/docs/search_tokens.py
chopdiff/docs/sizes.py
chopdiff/docs/text_doc.py
chopdiff/docs/token_diffs.py
chopdiff/docs/token_mapping.py
chopdiff/docs/wordtoks.py
chopdiff/html/__init__.py
chopdiff/html/extractor.py
chopdiff/html/html_in_md.py
chopdiff/html/html_plaintext.py
chopdiff/html/html_tags.py
chopdiff/html/timestamps.py
chopdiff/transforms/__init__.py
chopdiff/transforms/diff_filters.py
chopdiff/transforms/sliding_transforms.py
chopdiff/transforms/sliding_windows.py
chopdiff/transforms/window_settings.py
chopdiff/util/__init__.py
chopdiff/util/lemmatize.py
chopdiff/util/tiktoken_utils.py
chopdiff-0.2.6.dist-info/METADATA
chopdiff-0.2.6.dist-info/WHEEL
chopdiff-0.2.6.dist-info/entry_points.txt
chopdiff-0.2.6.dist-info/licenses/LICENSE
chopdiff-0.2.6.dist-info/RECORD
