Metadata-Version: 2.4
Name: chopdiff
Version: 0.2.6
Summary: Chunking, diff filtering, and windowed transforms of text to support LLM applications
Project-URL: Repository, https://github.com/jlevy/chopdiff
Author-email: Joshua Levy <joshua@cal.berkeley.edu>
License-Expression: MIT
License-File: LICENSE
Classifier: Development Status :: 4 - Beta
Classifier: Intended Audience :: Developers
Classifier: Operating System :: OS Independent
Classifier: Programming Language :: Python
Classifier: Programming Language :: Python :: 3
Classifier: Programming Language :: Python :: 3.11
Classifier: Programming Language :: Python :: 3.12
Classifier: Programming Language :: Python :: 3.13
Classifier: Typing :: Typed
Requires-Python: <4.0,>=3.11
Requires-Dist: cydifflib>=1.2.0
Requires-Dist: flowmark>=0.5.3
Requires-Dist: funlog>=0.2.1
Requires-Dist: prettyfmt>=0.3.0
Requires-Dist: regex>=2024.11.6
Requires-Dist: selectolax>=0.3.32
Requires-Dist: strif>=2.1.0
Requires-Dist: tiktoken>=0.9.0
Provides-Extra: extras
Requires-Dist: simplemma>=1.1.2; extra == 'extras'
